pgraph/__init__.py
pgraph/backend_config.py
pgraph/celeryconfig.py
pgraph/config.py
pgraph/run.py
pgraph/tasks.py
pgraph/views.py
pgraph/static/theme.css
pgraph/static/linkdraw/examples/css/style.css
pgraph/static/linkdraw/examples/html/demo.html
pgraph/static/linkdraw/examples/html/sample.html
pgraph/static/linkdraw/examples/html/template.html
pgraph/static/linkdraw/examples/js/sample1.js
pgraph/static/linkdraw/examples/js/sample10.js
pgraph/static/linkdraw/examples/js/sample11.js
pgraph/static/linkdraw/examples/js/sample12.js
pgraph/static/linkdraw/examples/js/sample13.js
pgraph/static/linkdraw/examples/js/sample2.js
pgraph/static/linkdraw/examples/js/sample3.js
pgraph/static/linkdraw/examples/js/sample4.js
pgraph/static/linkdraw/examples/js/sample5.js
pgraph/static/linkdraw/examples/js/sample6.js
pgraph/static/linkdraw/examples/js/sample7.js
pgraph/static/linkdraw/examples/js/sample8.js
pgraph/static/linkdraw/examples/js/sample9.js
pgraph/static/linkdraw/src/js/linkdraw.js
pgraph/static/linkdraw/tests/index.html
pgraph/static/linkdraw/tests/test_linkdraw.js
pgraph/static/linkdraw/utils/pre-commit.txt
pgraph/templates/config.pt
pgraph/templates/error.pt
pgraph/templates/graph.pt
pgraph/templates/index.pt
pgraph/templates/layout.pt
pgraph/templates/search.pt
pgraph-1.0.3.dist-info/LICENSE
pgraph-1.0.3.dist-info/METADATA
pgraph-1.0.3.dist-info/WHEEL
pgraph-1.0.3.dist-info/entry_points.txt
pgraph-1.0.3.dist-info/top_level.txt
pgraph-1.0.3.dist-info/RECORD
