Metadata-Version: 2.1
Name: pgraph
Version: 1.0.3
Summary: Drawing graph of the dependencies of Python packages
Home-page: https://github.com/mkouhei/pgraph
Author: Kouhei Maeda
Author-email: mkouhei@palmtb.net
License: UNKNOWN
Platform: UNKNOWN
Classifier: Development Status :: 4 - Beta
Classifier: Intended Audience :: Developers
Classifier: Framework :: Pyramid
Classifier: License :: OSI Approved :: GNU General Public License v3 or later (GPLv3+)
Classifier: Programming Language :: Python
Classifier: Programming Language :: Python :: 3
Classifier: Programming Language :: Python :: 3.8
Classifier: Programming Language :: Python :: Implementation :: CPython
Classifier: Topic :: Internet :: WWW/HTTP
Classifier: Topic :: Internet :: WWW/HTTP :: WSGI :: Application
Requires-Dist: celery
Requires-Dist: pip (<21.0,>=20.0)
Requires-Dist: py-deps (>=1.0.0)
Requires-Dist: pyramid
Requires-Dist: pyramid-chameleon
Requires-Dist: setuptools (<47.0,>=46.0)
Provides-Extra: development
Requires-Dist: mock ; extra == 'development'
Requires-Dist: pyramid-debugtoolbar ; extra == 'development'
Requires-Dist: webtest ; extra == 'development'
Provides-Extra: heroku
Requires-Dist: PasteDeploy ; extra == 'heroku'
Requires-Dist: newrelic ; extra == 'heroku'
Requires-Dist: psycopg2 ; extra == 'heroku'
Requires-Dist: pylibmc ; extra == 'heroku'
Requires-Dist: sqlalchemy ; extra == 'heroku'
Provides-Extra: rest
Requires-Dist: Sphinx ; extra == 'rest'
